setup.py
probdistri_gausbino/Binomialdistribution.py
probdistri_gausbino/Gaussiandistribution.py
probdistri_gausbino/Generaldistribution.py
probdistri_gausbino/__init__.py
probdistri_gausbino.egg-info/PKG-INFO
probdistri_gausbino.egg-info/SOURCES.txt
probdistri_gausbino.egg-info/dependency_links.txt
probdistri_gausbino.egg-info/not-zip-safe
probdistri_gausbino.egg-info/top_level.txt